{"relations":{"projects":{"count":136,"empty":false},
    "workexceptionsclassifications":{"count":1,"empty":false},
    "lifecyclestages":{"count":4,"empty":false},
    "companies":{"count":1,"empty":false},
    "updateprogressby":{"count":2,"empty":false},
    "schedulestatuses":{"count":5,"empty":false},
    "adminrole":{"count":1,"empty":false},
    "issuesubclassification":{"count":7,"empty":false},
    "workflowtransitionactions":{"count":4,"empty":false},
    "planitemclassifications":{"count":1,"empty":false},
    "physicalquantities":{"count":11,"empty":false},
    "importdefimporttypes":{"count":2,"empty":false},
    "projecttypes":{"count":8,"empty":false},"rfitypes":{"count":4,"empty":false},
    "importcolumntypes":{"count":9,"empty":false},"planitemstatuses":{"count":5,"empty":false},
    "traversables":{"count":481,"empty":false},"resourceclassifications":{"count":29,"empty":false},
    "planitemtypes":{"count":6,"empty":false},"externalsystems":{"count":23,"empty":false},
    "integrationenvironments":{"count":5,"empty":false},"classdefinitions":{"count":129,"empty":false},
    "reporttemplates":{"count":3,"empty":false},"issueclassifications":{"count":1,"empty":false},"quantificationproperties":{"count":66,"empty":false},"dateformats":{"count":6,"empty":false},"authproviders":{"count":1,"empty":false},"workflowclassdefinitions":{"count":2,"empty":false},"structitems":{"count":0,"empty":true},"authenticationtypes":{"count":2,"empty":false},"quantityrecipes":{"count":69,"empty":false},"ifcproperties":{"count":0,"empty":true},"planitemrecipes":{"count":112,"empty":false},"queries":{"count":12,"empty":false},"usertemplates":{"count":1,"empty":false},"calendars":{"count":7,"empty":false},"p6syncstatus":{"count":3,"empty":false},"allclassifications":{"count":205,"empty":false},"numberseparators":{"count":3,"empty":false},"currencies":{"count":47,"empty":false},"costitemtype":{"count":2,"empty":false},"reports":{"count":0,"empty":true},"folders":{"count":1,"empty":false},"documents":{"count":136,"empty":false},"planitempercentcompletetypes":{"count":3,"empty":false},"importdefs":{"count":17,"empty":false},"taggeditemclassifications":{"count":1,"empty":false},"issuestatuses":{"count":6,"empty":false},"dateseparators":{"count":3,"empty":false},"viewset":{"count":0,"empty":true},"globalresourceclassifications":{"count":1,"empty":false},"yearformats":{"count":2,"empty":false},"workflowactivityrecordstates":{"count":2,"empty":false},"estimatestatus":{"count":3,"empty":false},"estimatetype":{"count":4,"empty":false},"planitemprimaryconstrainttypes":{"count":9,"empty":false},"projecttemplates":{"count":1,"empty":false},"quantificationpropertytypes":{"count":3,"empty":false},"weightageoptions":{"count":2,"empty":false},"numbergroupings":{"count":2,"empty":false},"resourcetypes":{"count":2386,"empty":false},"pointclassifications":{"count":1,"empty":false},"subscriptiontypes":{"count":2,"empty":false},"workflowuserplaceholders":{"count":1,"empty":false},"modules":{"count":19,"empty":false},"users":{"count":186,"empty":false},"pbsclassifications":{"count":1,"empty":false},"timeformats":{"count":2,"empty":false},"planitempurpose":{"count":7,"empty":false},"transactionnodestatus":{"count":5,"empty":false},"userlanguagepath":{"count":5,"empty":false},"unitsystems":{"count":2,"empty":false},"importcolumngrouptypes":{"count":2,"empty":false},"integrationsystems":{"count":5,"empty":false},"planitemsecondaryconstrainttypes":{"count":4,"empty":false},"modelstatuses":{"count":5,"empty":false},"importcolumnimporttypes":{"count":4,"empty":false},"integrationtypes":{"count":4,"empty":false},"viewstatuses":{"count":3,"empty":false},"subscriptionintervals":{"count":5,"empty":false},"ecosyscoststatus":{"count":4,"empty":false},"ecosyssyncstatus":{"count":3,"empty":false},"issuepriorities":{"count":4,"empty":false},"mappings":{"count":4,"empty":false},"disciplines":{"count":11,"empty":false},"queues":{"count":8,"empty":false},"importdeftypes":{"count":2,"empty":false},"documentclassifications":{"count":1,"empty":false},"locations":{"count":58,"empty":false},"_stagingarea":{"count":1,"empty":false},"drawingversions":{"count":3,"empty":false}},
"links":{"self":"/tenant","traversed":"/tenant"},
"object":{"uid":"732882b4-a9e0-4b98-9fb6-233401c7e066",
    "edited_by_role":"062943c7-7a00-4612-b9ac-100922a7106d",
    "name":"GMT","created_date":"2019-10-17T06:48:38.046Z",
    "display_name":"GTM","edited_date":"2019-10-17T10:25:16.630Z",
    "created_by":"7e817f57-3ae4-4a7b-b984-f7862607f337",
    "edited_by":"c2220c36-dfe1-43fc-9632-15803eb43e16"}
}